pydbvolve/__init__.py
pydbvolve-1.0.2.data/scripts/pydbvolve
pydbvolve-1.0.2.dist-info/DESCRIPTION.rst
pydbvolve-1.0.2.dist-info/METADATA
pydbvolve-1.0.2.dist-info/RECORD
pydbvolve-1.0.2.dist-info/WHEEL
pydbvolve-1.0.2.dist-info/metadata.json
pydbvolve-1.0.2.dist-info/top_level.txt
