Metadata-Version: 2.0
Name: pydbvolve
Version: 1.0.2
Summary: Database migrations
Home-page: https://github.com/Teamworksapp/pydbvolve
Author: Teamworksapp
Author-email: teamworks_pypi@teamworks.com
License: MIT
Keywords: database migration sql python python3 pydbvolve
Platform: UNKNOWN
Classifier: Development Status :: 5 - Production/Stable
Classifier: Intended Audience :: Developers
Classifier: Intended Audience :: System Administrators
Classifier: Topic :: Utilities
Classifier: Topic :: Database
Classifier: License :: OSI Approved :: MIT License
Classifier: Programming Language :: Python :: 3.5
